cli/__init__.py
cli/helpers.py
cli/main.py
cli/requirements.txt
cli/templates/job_matrix_overview.md
cli/templates/skill_matrix_overview.md
fledger-0.1.1.dist-info/METADATA
fledger-0.1.1.dist-info/WHEEL
fledger-0.1.1.dist-info/entry_points.txt
fledger-0.1.1.dist-info/licenses/LICENSE
fledger-0.1.1.dist-info/RECORD
