Metadata-Version: 2.3
Name: fledger
Version: 0.1.1
Summary: Fledger is a Python Framework that simplifies software engineering and development under standards. 
Project-URL: Documentation, https://github.com/jasonburt/fledger/blob/main/README.md
Project-URL: Issues, https://github.com/jasonburt/fledger/issues
Project-URL: Source, https://github.com/jasonburt/fledger
Author-email: Jason Burt <jason2burt+fledger@gmail.com>
License-Expression: Apache-2.0
License-File: LICENSE
Classifier: Development Status :: 4 - Beta
Classifier: Programming Language :: Python
Classifier: Programming Language :: Python :: 3.8
Classifier: Programming Language :: Python :: 3.9
Classifier: Programming Language :: Python :: 3.10
Classifier: Programming Language :: Python :: 3.11
Classifier: Programming Language :: Python :: 3.12
Classifier: Programming Language :: Python :: Implementation :: CPython
Classifier: Programming Language :: Python :: Implementation :: PyPy
Requires-Python: >=3.8
Requires-Dist: typer==0.3.2
